tests/__init__.py
tests/conftest.py
tests/test_client.py
tests/test_leaflet.py
tests/test_utilities.py
tileserver/__init__.py
tileserver/__main__.py
tileserver/_version.py
tileserver/examples.py
tileserver/leaflet.py
tileserver/report.py
tileserver/server.py
tileserver/utilities.py
tileserver/application/__init__.py
tileserver/application/rest.py
tileserver/application/urls.py
tileserver/application/views.py
tileserver/application/static/js/cesium.js
tileserver/application/static/js/geojs.js
tileserver/application/static/js/geojsControls.js
tileserver/application/static/styles/cesium.css
tileserver/application/static/styles/geojs.css
tileserver/application/static/styles/style.css
tileserver/application/templates/base.html
tileserver/application/templates/cesiumViewer.html
tileserver/application/templates/geojsViewer.html
tileserver/application/templates/_include/cesium.html
tileserver/application/templates/_include/geojs.html
tileserver/application/templates/_include/geojsControls.html
tileserver/data/aws_elevation_tiles_prod.xml
tileserver/data/bahamas_rgb.tif
tileserver/data/frmt_wms_arcgis_mapserver_tms.xml
tileserver/data/frmt_wms_bluemarble_s3_tms.xml
tileserver/data/frmt_wms_virtualearth.xml
flask_tileserver-0.2.3.dist-info/LICENSE
flask_tileserver-0.2.3.dist-info/METADATA
flask_tileserver-0.2.3.dist-info/WHEEL
flask_tileserver-0.2.3.dist-info/top_level.txt
flask_tileserver-0.2.3.dist-info/RECORD
