Metadata-Version: 2.1
Name: flask-tileserver
Version: 0.2.3
Summary: Locally serve geospatial raster tiles in the Slippy Map standard.
Home-page: https://github.com/banesullivan/flask-tileserver
Author: Bane Sullivan
Author-email: banesullivan@gmail.com
License: UNKNOWN
Platform: UNKNOWN
Classifier: Development Status :: 3 - Alpha
Classifier: License :: OSI Approved :: MIT License
Classifier: Operating System :: OS Independent
Classifier: Programming Language :: Python :: 3
Classifier: Programming Language :: Python :: 3.8
Classifier: Programming Language :: Python
Requires-Python: >=3.6
Requires-Dist: click
Requires-Dist: flask
Requires-Dist: Flask-Caching
Requires-Dist: furl
Requires-Dist: GDAL
Requires-Dist: large-image
Requires-Dist: large-image-source-gdal
Requires-Dist: requests
Requires-Dist: scooby
Provides-Extra: leaflet
Requires-Dist: ipyleaflet ; extra == 'leaflet'
